async_sync/__init__.py
async_sync/core.py
async_sync/py.typed
async_sync-0.1.1.dist-info/METADATA
async_sync-0.1.1.dist-info/WHEEL
async_sync-0.1.1.dist-info/licenses/LICENSE
async_sync-0.1.1.dist-info/RECORD
