Metadata-Version: 2.4
Name: async-sync
Version: 0.1.1
Summary: async-sync - Elegant conversion between Python sync and async code
Project-URL: Homepage, https://github.com/Haskely/async-sync
Project-URL: Repository, https://github.com/Haskely/async-sync
Project-URL: Documentation, https://github.com/Haskely/async-sync#readme
Project-URL: Bug Tracker, https://github.com/Haskely/async-sync/issues
Project-URL: Change Log, https://github.com/Haskely/async-sync/blob/main/CHANGELOG.md
Author-email: Haskely <Haskely@live.com>
License-File: LICENSE
Requires-Python: >=3.10
